chapar/__init__.py
chapar/__main__.py
chapar/message_broker.py
chapar/schema_repo.py
chapar-0.7.dist-info/METADATA
chapar-0.7.dist-info/WHEEL
chapar-0.7.dist-info/entry_points.txt
chapar-0.7.dist-info/top_level.txt
chapar-0.7.dist-info/RECORD
